mtcli_market/__init__.py
mtcli_market/cli.py
mtcli_market/conf.py
mtcli_market/controller.py
mtcli_market/market_config.py
mtcli_market/model.py
mtcli_market/plugin.py
mtcli_market/view.py
mtcli_market-1.2.2.dist-info/entry_points.txt
mtcli_market-1.2.2.dist-info/licenses/LICENSE
mtcli_market-1.2.2.dist-info/METADATA
mtcli_market-1.2.2.dist-info/WHEEL
mtcli_market-1.2.2.dist-info/RECORD
